{
    "mains": [
        {
            "icon": "/assets/images/game/ssbu/characters/zelda.png",
            "name": "Zelda"
        }
    ],
    "name": "Leo",
    "rank": {
        "liga_ultra_arcade_s1": {
            "rank": "24",
            "score": "4"
        },
        "prbth": {
            "rank": 101,
            "score": 32
        },
        "ssbuse": {
            "rank": "3",
            "score": "1616"
        }
    },
    "tournament_points": [
        16,
        16
    ],
    "tournaments": [
        {
            "name": "SERGIPE BEACH TOURNAMENT - ROUND ROBIN POOLS",
            "placing": "3",
            "points": 16,
            "rank": "D"
        },
        {
            "name": "SERGIPE BEACH TOURNAMENT",
            "placing": "3",
            "points": 16,
            "rank": "D"
        }
    ]
}