{
    "best_player_character": {
        "Banjo & Kazooie": {
            "apid": 199,
            "bestPlayerCharacter": {
                "ligamscg": [
                    "Banjo & Kazooie",
                    "Banjo-Kazooie"
                ],
                "prbth": [
                    "Banjo & Kazooie",
                    "Banjo-Kazooie"
                ]
            },
            "braacket_links": [
                "homeonline:3E2C0089-1D24-4B2F-B417-807AB2FDE552",
                "prbth:9E1C2154-EC62-4D41-8329-9778D2066778",
                "ligamscg:30BCCE24-0BF8-4B35-B76F-FDAE0CBDBCED"
            ],
            "character_usage": {
                "Banjo-Kazooie": 36,
                "Kirby": 2,
                "Luigi": 22
            },
            "city": "Campo Grande",
            "country": "Brazil",
            "country_code": "BR",
            "full_name": "Daniel Fajardo",
            "mains": [
                "Banjo-Kazooie",
                "Luigi"
            ],
            "name": "DANIBOY",
            "org": "",
            "rank": "2",
            "smashgg_id": 884804,
            "smashgg_image": "https://images.smash.gg/images/user/884804/image-7fe1970f417c2aa056da937c864bfb71.jpg",
            "smashgg_slug": "user/5cfec2fa",
            "state": "AL",
            "twitter": "farjados"
        },
        "Bowser": {
            "apid": 398,
            "bestPlayerCharacter": {
                "ligamscg": [
                    "Bowser",
                    "Bowser"
                ]
            },
            "braacket_links": [
                "homeonline:766FD45A-1265-4332-ABE7-A42D1D637D8B",
                "prbth:2ADD214D-6CC4-4D63-BB84-7C3F24F9EA34",
                "ligamscg:0023D303-1DBD-41C0-A9A7-61DB5ABA05CE"
            ],
            "character_usage": {
                "Bowser": 20,
                "Chrom": 3,
                "Ganondorf": 20,
                "Hero": 8,
                "Lucina": 2
            },
            "city": "Campo Grande",
            "country": "Brazil",
            "country_code": "BR",
            "full_name": null,
            "mains": [
                "Bowser",
                "Chrom",
                "Ganondorf",
                "Hero"
            ],
            "name": "Headpat",
            "org": "Nyoron",
            "rank": "9",
            "smashgg_id": 998215,
            "smashgg_image": "https://images.smash.gg/images/user/998215/image-c715f38690d1a86d78fe21c7be868740.png",
            "smashgg_slug": "user/392341bf",
            "state": "AL",
            "twitter": "Headpat2"
        },
        "Captain Falcon": {
            "apid": 2500,
            "bestPlayerCharacter": {
                "ligamscg": [
                    "Captain Falcon",
                    "Captain Falcon"
                ]
            },
            "braacket_links": [
                "ligamscg:E395AD8C-8A52-4AC6-8E5F-695491689722"
            ],
            "mains": [
                "Captain Falcon",
                "Little Mac",
                "Samus"
            ],
            "name": "Souwer",
            "rank": "20"
        },
        "Corrin": {
            "apid": 1287,
            "bestPlayerCharacter": {
                "ligamscg": [
                    "Corrin",
                    "Corrin"
                ]
            },
            "braacket_links": [
                "prbth:CE397BE4-9E7B-48BA-958E-D0BBA69E7ACB",
                "ligamscg:81CA19FD-49CD-434B-9258-3D10A59F508A"
            ],
            "character_usage": {
                "Byleth": 1,
                "Corrin": 3
            },
            "city": "Campo Grande",
            "country": "Brazil",
            "country_code": "BR",
            "full_name": null,
            "mains": [
                "Corrin",
                "Byleth"
            ],
            "name": "FL",
            "org": "SrAnjoBoy",
            "rank": "16",
            "smashgg_id": 1010609,
            "smashgg_slug": "user/61d3eaf7",
            "state": "AL"
        },
        "Dark Pit": {
            "apid": 1354,
            "bestPlayerCharacter": {
                "ligamscg": [
                    "Dark Pit",
                    "Dark Pit"
                ],
                "prbth": [
                    "Dark Pit",
                    "Dark Pit"
                ]
            },
            "braacket_links": [
                "prbth:FBA0D105-D3E5-45F9-9D4A-8FFC5E7287AD",
                "ligamscg:D3F3F0DB-EADE-4C86-9438-75CC8D457D32"
            ],
            "character_usage": {
                "Dark Pit": 17,
                "Yoshi": 2
            },
            "full_name": "Luiz Gustavo Mendon\u00e7a",
            "mains": [
                "Dark Pit",
                "Yoshi"
            ],
            "name": "Tavito",
            "org": "",
            "rank": "15",
            "smashgg_id": 997491,
            "smashgg_image": "https://images.smash.gg/images/user/997491/image-8bf001aa4b1767f6d81cc5f02e4c42fd.jpeg",
            "smashgg_slug": "user/df299f93"
        },
        "Fox": {
            "apid": 2498,
            "bestPlayerCharacter": {
                "ligamscg": [
                    "Fox",
                    "Fox"
                ]
            },
            "braacket_links": [
                "ligamscg:D1E0C1BD-DEC0-43CB-B0F5-8DC22B8A19DA"
            ],
            "mains": [
                "Fox"
            ],
            "name": "Garden",
            "rank": "18"
        },
        "Greninja": {
            "apid": 1033,
            "bestPlayerCharacter": {
                "ligamscg": [
                    "Greninja",
                    "Greninja"
                ],
                "prbth": [
                    "Greninja",
                    "Greninja"
                ]
            },
            "braacket_links": [
                "prbth:5EB3E92F-ACA2-4289-9358-E005F09C2A7A",
                "ligamscg:C94ABAC0-0F5A-4769-AC98-66C18C7B34BF"
            ],
            "character_usage": {
                "Bowser": 1,
                "Byleth": 5,
                "Greninja": 12,
                "Lucina": 10
            },
            "city": "Campo Grande",
            "country": "Brazil",
            "country_code": "BR",
            "full_name": "Felipe R.",
            "mains": [
                "Greninja",
                "Lucina"
            ],
            "name": "Kurobo",
            "org": "LMS",
            "rank": "6",
            "smashgg_id": 276084,
            "smashgg_image": "https://images.smash.gg/images/user/276084/image-337232ecc96a1d0e1e073e1ca56c3a54.png",
            "smashgg_slug": "user/70884a76",
            "state": "AL",
            "twitch": "KuroboKun",
            "twitter": "KuroboKun"
        },
        "Hero": {
            "apid": 813,
            "bestPlayerCharacter": {
                "ligamscg": [
                    "Hero",
                    "Hero"
                ]
            },
            "braacket_links": [
                "homeonline:F9ED906A-A540-43B2-AF62-3611D9CE9506",
                "prbth:8DA61E58-52B0-41A2-B87A-A95EEB9E3CCA",
                "ligamscg:DFCF5505-3E29-4FD6-A418-5C40C9BF7562"
            ],
            "character_usage": {
                "Hero": 39,
                "Kirby": 6,
                "Ness": 11,
                "Ridley": 2
            },
            "full_name": "Gabriel Costa",
            "mains": [
                "Hero",
                "Ness"
            ],
            "name": "ShyKokiri",
            "org": "SCGMS",
            "rank": "7",
            "smashgg_id": 997481,
            "smashgg_image": "https://images.smash.gg/images/user/997481/image-4ae8518a8a7186790edb9c36419d8142.jpeg",
            "smashgg_slug": "user/c7b1b649",
            "twitch": "shykokiri"
        },
        "Jigglypuff": {
            "apid": 1073,
            "bestPlayerCharacter": {
                "ligamscg": [
                    "Jigglypuff",
                    "Jigglypuff"
                ]
            },
            "braacket_links": [
                "prbth:71CF1198-13BD-4B63-B445-E13349F4B5B5",
                "ligamscg:F1D3570F-9535-4760-8DE0-FFDB52F8D2E4"
            ],
            "character_usage": {
                "Donkey Kong": 3,
                "Jigglypuff": 21,
                "Mii Gunner": 6,
                "Palutena": 1,
                "Samus": 1
            },
            "full_name": "SYSTEM SURVEY COMPLETE",
            "mains": [
                "Jigglypuff",
                "Mii Gunner"
            ],
            "name": "Stellaris",
            "org": "2B4U",
            "rank": "12",
            "smashgg_id": 1000390,
            "smashgg_image": "https://images.smash.gg/images/user/1000390/image-3594a09489fc85f614326c780bfdc159.png",
            "smashgg_slug": "user/5c1c6535",
            "twitter": "845r845"
        },
        "Joker": {
            "apid": 798,
            "bestPlayerCharacter": {
                "ligamscg": [
                    "Joker",
                    "Joker"
                ]
            },
            "braacket_links": [
                "homeonline:F4855B5B-30B7-482C-9E2D-43CA54CDCBE3",
                "prbth:5E74322A-5170-4ACB-BECE-585724023A9D",
                "ligamscg:D0A488BD-C4B1-44D1-B45F-F4DD154F07BD"
            ],
            "character_usage": {
                "Fox": 17,
                "Joker": 19,
                "Pit": 1,
                "Roy": 1,
                "Sheik": 8
            },
            "city": "Campo Grande",
            "country": "Brazil",
            "country_code": "BR",
            "full_name": "Yuri Ricarte",
            "mains": [
                "Joker",
                "Fox"
            ],
            "name": "Marte",
            "org": "",
            "rank": "5",
            "smashgg_id": 870755,
            "smashgg_slug": "user/1c789ea3",
            "state": "AL"
        },
        "Ken": {
            "apid": 208,
            "bestPlayerCharacter": {
                "ligamscg": [
                    "Ken",
                    "Ken"
                ],
                "prbth": [
                    "Ken",
                    "Ken"
                ]
            },
            "braacket_links": [
                "homeonline:4152D727-DEEF-43CE-9820-803C19D16F9F",
                "prbth:C5A71868-0149-4FD6-AA60-454B5807C6EB",
                "ligamscg:6F063704-FE50-469E-9041-D51B4DFB406C"
            ],
            "character_usage": {
                "Ken": 11,
                "Link": 4,
                "Zero Suit Samus": 7
            },
            "city": "Campo Grande",
            "country": "Brazil",
            "country_code": "BR",
            "full_name": "Davi Romeo",
            "mains": [
                "Ken",
                "Zero Suit Samus"
            ],
            "name": "Signas",
            "org": "Flechinha",
            "rank": "3",
            "smashgg_id": 975198,
            "smashgg_image": "https://images.smash.gg/images/user/975198/image-fcb0be2972d0613c351eb6ed7f6615f8.jpeg",
            "smashgg_slug": "user/03d10cc1",
            "state": "AL",
            "twitch": "daviromeo"
        },
        "King K. Rool": {
            "apid": 494,
            "bestPlayerCharacter": {
                "ligamscg": [
                    "King K. Rool",
                    "King K Rool"
                ]
            },
            "braacket_links": [
                "homeonline:9506FDE2-8948-4B5D-B89F-B2676B742C97",
                "prbth:13554F8B-FFB6-47E3-93EB-AA636A3970AF",
                "ligamscg:C953E875-1133-4E9F-93C9-9A7FB52FF4C0"
            ],
            "character_usage": {
                "Corrin": 5,
                "Incineroar": 14,
                "King K. Rool": 18,
                "Toon Link": 2
            },
            "country": "Brazil",
            "country_code": "BR",
            "full_name": "David Carlos Rodrigues",
            "mains": [
                "King K Rool",
                "Incineroar"
            ],
            "name": "Dvd",
            "org": "Flechinha",
            "rank": "19",
            "smashgg_id": 1010379,
            "smashgg_slug": "user/3ae79e25",
            "twitch": "dvdn00b"
        },
        "Link": {
            "apid": 490,
            "bestPlayerCharacter": {
                "ligamscg": [
                    "Link",
                    "Link"
                ]
            },
            "braacket_links": [
                "homeonline:93967379-B789-4074-9743-73D3AB43C13A",
                "prbth:EA8A3DB1-BF73-4F48-BFDE-8B03E08879A5",
                "ligamscg:C7DE29BF-A859-44FF-BD18-FF79D10E1FC6"
            ],
            "character_usage": {
                "Captain Falcon": 1,
                "Chrom": 1,
                "Cloud": 6,
                "Joker": 4,
                "Ken": 4,
                "Link": 32,
                "Terry": 1,
                "Wolf": 1,
                "Young Link": 6
            },
            "country": "Brazil",
            "country_code": "BR",
            "full_name": "Aleh Padilha",
            "mains": [
                "Link",
                "Cloud"
            ],
            "name": "Aleh Padilha",
            "org": "Flechinha",
            "rank": "4",
            "smashgg_id": 864193,
            "smashgg_slug": "user/483f4e6c",
            "twitch": "alehpadilha"
        },
        "Lucas": {
            "apid": 341,
            "bestPlayerCharacter": {
                "ligamscg": [
                    "Lucas",
                    "Lucas"
                ]
            },
            "braacket_links": [
                "homeonline:65A77980-DC36-4921-972A-72CA780AAD3E",
                "prbth:B5B8017C-1369-42FE-9B36-3AF3BF38123A",
                "ligamscg:E6866271-A5DD-4730-A1DF-D2068B05484D"
            ],
            "character_usage": {
                "Bowser Jr.": 1,
                "Cloud": 3,
                "Dark Samus": 1,
                "Isabelle": 1,
                "Joker": 1,
                "Link": 1,
                "Little Mac": 1,
                "Lucas": 14,
                "Mr. Game & Watch": 1,
                "Richter": 1,
                "Toon Link": 2,
                "Villager": 2
            },
            "city": "campo grande- ms",
            "country": "Brazil",
            "country_code": "BR",
            "full_name": "lucas prieto",
            "mains": [
                "Lucas",
                "Cloud"
            ],
            "name": "Luvas",
            "org": "UwU",
            "rank": "10",
            "smashgg_id": 1000059,
            "smashgg_image": "https://images.smash.gg/images/user/1000059/image-a221e8ed7a417cf5e10957f9e660e0d0.jfif",
            "smashgg_slug": "user/71920764"
        },
        "Lucina": {
            "apid": 2499,
            "bestPlayerCharacter": {
                "ligamscg": [
                    "Lucina",
                    "Lucina"
                ]
            },
            "braacket_links": [
                "ligamscg:D69A08F1-0DC5-4833-A3F2-4F37D14E3536"
            ],
            "mains": [
                "Lucina"
            ],
            "name": "Thaisa",
            "rank": "21"
        },
        "Mega Man": {
            "apid": 513,
            "bestPlayerCharacter": {
                "ligamscg": [
                    "Mega Man",
                    "Mega Man"
                ]
            },
            "braacket_links": [
                "homeonline:9A64F15A-EECD-40AF-9CEE-601D86848057",
                "prbth:C9856B38-4FAF-4D7B-ABEF-DB9ECCE1CE62",
                "ligamscg:6479E64A-E9D0-402D-B2AB-8BE8F2033475"
            ],
            "character_usage": {
                "Mega Man": 49,
                "Min Min": 20
            },
            "city": "Campo Grande",
            "country": "Brazil",
            "country_code": "BR",
            "full_name": "Jos\u00e9 Paulo Santos Nogeuria",
            "mains": [
                "Mega Man",
                "Min Min"
            ],
            "name": "Dagoth Ur",
            "org": "LMS",
            "rank": "13",
            "smashgg_id": 1000378,
            "smashgg_image": "https://images.smash.gg/images/user/1000378/image-7fa8a4bec8728aa5bb0992339adb80fc.jpeg",
            "smashgg_slug": "user/ef473743",
            "state": "AL",
            "twitch": "jozildu",
            "twitter": "RSkyrim3"
        },
        "PAC-MAN": {
            "apid": 68,
            "bestPlayerCharacter": {
                "ligamscg": [
                    "PAC-MAN",
                    "Pac Man"
                ]
            },
            "braacket_links": [
                "homeonline:1648379F-6236-41E6-928D-DA814C4F8AF0",
                "prbth:6FA29429-8C04-460F-9914-5AF55D7671DC",
                "ligamscg:CC6863B2-D244-43C1-82E3-51997B02B3A9"
            ],
            "character_usage": {
                "Byleth": 2,
                "Dr. Mario": 1,
                "Ganondorf": 2,
                "Isabelle": 4,
                "Little Mac": 2,
                "Pac-Man": 23,
                "Robin": 19,
                "Toon Link": 3
            },
            "country": "Brazil",
            "country_code": "BR",
            "full_name": "Gabriel Yougo Tamasato Sanch",
            "mains": [
                "Pac Man",
                "Robin"
            ],
            "name": "GyoUranio",
            "org": "Flechinha",
            "rank": "1",
            "smashgg_id": 1010441,
            "smashgg_image": "https://images.smash.gg/images/user/1010441/image-f8a42fb76d408ffaaea5439cc9c85cfa.jpg",
            "smashgg_slug": "user/aab48499",
            "twitch": "kiirogyo"
        },
        "Piranha Plant": {
            "apid": 291,
            "bestPlayerCharacter": {
                "homeonline": [
                    "Piranha Plant",
                    "Piranha Plant"
                ],
                "ligamscg": [
                    "Piranha Plant",
                    "Piranha Plant"
                ]
            },
            "braacket_links": [
                "homeonline:583C4361-F153-4073-BB51-2CA346708EF8",
                "prbth:1524DDAE-6368-47D8-A085-1F4FFBB768AF",
                "ligamscg:AB0316B3-16CD-475A-9C93-0DD69ABABCDB"
            ],
            "character_usage": {
                "Piranha Plant": 61
            },
            "city": "campo grande, ms",
            "country": "Brazil",
            "country_code": "BR",
            "discord": "herobrinee#8134",
            "full_name": "Dimas Shakihama",
            "mains": [
                "Piranha Plant"
            ],
            "name": "sandwich :)",
            "org": "",
            "rank": "8",
            "smashgg_id": 1006025,
            "smashgg_image": "https://images.smash.gg/images/user/1006025/image-aab187e1f287825fd63850b88d7ea169.jpg",
            "smashgg_slug": "user/8bd2df10",
            "twitch": "snasdvish",
            "twitter": "sansdvish"
        },
        "R.O.B.": {
            "apid": 963,
            "bestPlayerCharacter": {
                "ligamscg": [
                    "R.O.B.",
                    "Rob"
                ]
            },
            "braacket_links": [
                "prbth:403C005E-BE49-44CE-8C92-6AFBFBDD831F",
                "ligamscg:1653A634-17BC-4B0C-B0CB-C8B84BE9ECAA"
            ],
            "character_usage": {
                "Corrin": 1,
                "R.O.B.": 3
            },
            "country": "Brazil",
            "country_code": "BR",
            "full_name": "Alexandre Liborio",
            "mains": [
                "Rob",
                "Corrin"
            ],
            "name": "Karones",
            "org": null,
            "rank": "22",
            "smashgg_id": 997483,
            "smashgg_slug": "user/7d3ab6cf"
        },
        "Rosalina & Luma": {
            "apid": 961,
            "bestPlayerCharacter": {
                "ligamscg": [
                    "Rosalina & Luma",
                    "Rosalina And Luma"
                ]
            },
            "braacket_links": [
                "prbth:3E5E88C4-D358-4F96-9238-68BA036C5CC8",
                "ligamscg:32B064E7-C77C-4403-A83B-2AEF764C62B8"
            ],
            "character_usage": {
                "Bowser Jr.": 1,
                "Diddy Kong": 1,
                "Mii Gunner": 5,
                "Mr. Game & Watch": 2,
                "Rosalina": 9
            },
            "country": "Brazil",
            "country_code": "BR",
            "full_name": "Jean Torres",
            "mains": [
                "Rosalina And Luma",
                "Mii Gunner"
            ],
            "name": "Alteron",
            "org": null,
            "rank": "11",
            "smashgg_id": 164387,
            "smashgg_slug": "user/03707f80"
        },
        "Samus": {
            "apid": 120,
            "bestPlayerCharacter": {
                "ligamscg": [
                    "Samus",
                    "Samus"
                ]
            },
            "braacket_links": [
                "homeonline:260BFCA6-5D57-4411-AD7F-0BC646AE07D0",
                "homeonline:E79CE505-D800-40F1-8FF8-3F1FA90D7165",
                "prbth:06BAA762-8EC8-45C3-BAA6-E7D3E8D07CBE",
                "ligamscg:BF11C8F2-7302-4A1C-B7AE-4D98F9578B7A"
            ],
            "character_usage": {
                "Ganondorf": 2,
                "Link": 2,
                "Samus": 35,
                "Zelda": 4
            },
            "city": "Campo Grande",
            "country": "Brazil",
            "country_code": "BR",
            "full_name": "DANIEL BEN YISRAEL ARAUJO E TALARICO",
            "mains": [
                "Samus",
                "Zelda"
            ],
            "name": "Nyanlatotepp",
            "org": "CGMS",
            "rank": "14",
            "smashgg_id": 1044598,
            "smashgg_image": "https://images.smash.gg/images/user/1044598/image-bfd07a12cfcfafff6554170b2d53d51e.jpg",
            "smashgg_slug": "user/bdcf5769",
            "state": "AL",
            "twitter": "Nyarlatotepp"
        }
    },
    "char_usage": {
        "Banjo & Kazooie": {
            "name": "Banjo-Kazooie",
            "secondary": 0,
            "usage": 1
        },
        "Bayonetta": {
            "name": "Bayonetta",
            "secondary": 0,
            "usage": 0
        },
        "Bowser": {
            "name": "Bowser",
            "secondary": 0,
            "usage": 1
        },
        "Bowser Jr.": {
            "name": "Bowser Jr",
            "secondary": 0,
            "usage": 0
        },
        "Byleth": {
            "name": "Byleth",
            "secondary": 1,
            "usage": 0
        },
        "Captain Falcon": {
            "name": "Captain Falcon",
            "secondary": 0,
            "usage": 1
        },
        "Chrom": {
            "name": "Chrom",
            "secondary": 1,
            "usage": 0
        },
        "Cloud": {
            "name": "Cloud",
            "secondary": 2,
            "usage": 0
        },
        "Corrin": {
            "name": "Corrin",
            "secondary": 1,
            "usage": 2
        },
        "Daisy": {
            "name": "Daisy",
            "secondary": 0,
            "usage": 0
        },
        "Dark Pit": {
            "name": "Dark Pit",
            "secondary": 0,
            "usage": 1
        },
        "Dark Samus": {
            "name": "Dark Samus",
            "secondary": 0,
            "usage": 0
        },
        "Diddy Kong": {
            "name": "Diddy Kong",
            "secondary": 0,
            "usage": 0
        },
        "Donkey Kong": {
            "name": "Donkey Kong",
            "secondary": 0,
            "usage": 0
        },
        "Dr. Mario": {
            "name": "Dr Mario",
            "secondary": 0,
            "usage": 0
        },
        "Duck Hunt": {
            "name": "Duck Hunt",
            "secondary": 0,
            "usage": 0
        },
        "Falco": {
            "name": "Falco",
            "secondary": 0,
            "usage": 0
        },
        "Fox": {
            "name": "Fox",
            "secondary": 1,
            "usage": 1
        },
        "Ganondorf": {
            "name": "Ganondorf",
            "secondary": 1,
            "usage": 0
        },
        "Greninja": {
            "name": "Greninja",
            "secondary": 0,
            "usage": 1
        },
        "Hero": {
            "name": "Hero",
            "secondary": 1,
            "usage": 1
        },
        "Ice Climbers": {
            "name": "Ice Climbers",
            "secondary": 0,
            "usage": 0
        },
        "Ike": {
            "name": "Ike",
            "secondary": 0,
            "usage": 0
        },
        "Incineroar": {
            "name": "Incineroar",
            "secondary": 1,
            "usage": 0
        },
        "Inkling": {
            "name": "Inkling",
            "secondary": 0,
            "usage": 0
        },
        "Isabelle": {
            "name": "Isabelle",
            "secondary": 0,
            "usage": 0
        },
        "Jigglypuff": {
            "name": "Jigglypuff",
            "secondary": 0,
            "usage": 1
        },
        "Joker": {
            "name": "Joker",
            "secondary": 0,
            "usage": 1
        },
        "Ken": {
            "name": "Ken",
            "secondary": 0,
            "usage": 1
        },
        "King Dedede": {
            "name": "King Dedede",
            "secondary": 0,
            "usage": 0
        },
        "King K. Rool": {
            "name": "King K Rool",
            "secondary": 0,
            "usage": 1
        },
        "Kirby": {
            "name": "Kirby",
            "secondary": 0,
            "usage": 0
        },
        "Link": {
            "name": "Link",
            "secondary": 0,
            "usage": 1
        },
        "Little Mac": {
            "name": "Little Mac",
            "secondary": 1,
            "usage": 0
        },
        "Lucario": {
            "name": "Lucario",
            "secondary": 0,
            "usage": 0
        },
        "Lucas": {
            "name": "Lucas",
            "secondary": 0,
            "usage": 1
        },
        "Lucina": {
            "name": "Lucina",
            "secondary": 2,
            "usage": 1
        },
        "Luigi": {
            "name": "Luigi",
            "secondary": 1,
            "usage": 0
        },
        "Mario": {
            "name": "Mario",
            "secondary": 0,
            "usage": 0
        },
        "Marth": {
            "name": "Marth",
            "secondary": 0,
            "usage": 0
        },
        "Mega Man": {
            "name": "Mega Man",
            "secondary": 0,
            "usage": 1
        },
        "Meta Knight": {
            "name": "Meta Knight",
            "secondary": 0,
            "usage": 0
        },
        "Mewtwo": {
            "name": "Mewtwo",
            "secondary": 0,
            "usage": 0
        },
        "Mii Fighter": {
            "name": "Mii Brawler",
            "secondary": 0,
            "usage": 0
        },
        "Mii Gunner": {
            "name": "Mii Gunner",
            "secondary": 2,
            "usage": 0
        },
        "Mii Swordfighter": {
            "name": "Mii Swordfighter",
            "secondary": 0,
            "usage": 0
        },
        "Min Min": {
            "name": "Min Min",
            "secondary": 1,
            "usage": 0
        },
        "Mr. Game & Watch": {
            "name": "Mr Game And Watch",
            "secondary": 0,
            "usage": 0
        },
        "Ness": {
            "name": "Ness",
            "secondary": 1,
            "usage": 0
        },
        "Olimar": {
            "name": "Olimar",
            "secondary": 0,
            "usage": 0
        },
        "PAC-MAN": {
            "name": "Pac Man",
            "secondary": 0,
            "usage": 1
        },
        "Palutena": {
            "name": "Palutena",
            "secondary": 0,
            "usage": 0
        },
        "Peach": {
            "name": "Peach",
            "secondary": 0,
            "usage": 0
        },
        "Pichu": {
            "name": "Pichu",
            "secondary": 0,
            "usage": 0
        },
        "Pikachu": {
            "name": "Pikachu",
            "secondary": 0,
            "usage": 0
        },
        "Piranha Plant": {
            "name": "Piranha Plant",
            "secondary": 0,
            "usage": 1
        },
        "Pit": {
            "name": "Pit",
            "secondary": 0,
            "usage": 0
        },
        "Pok\u00e9mon Trainer": {
            "name": "Pokemon Trainer",
            "secondary": 0,
            "usage": 0
        },
        "R.O.B.": {
            "name": "Rob",
            "secondary": 0,
            "usage": 1
        },
        "Richter": {
            "name": "Richter",
            "secondary": 0,
            "usage": 0
        },
        "Ridley": {
            "name": "Ridley",
            "secondary": 0,
            "usage": 0
        },
        "Robin": {
            "name": "Robin",
            "secondary": 1,
            "usage": 0
        },
        "Rosalina & Luma": {
            "name": "Rosalina And Luma",
            "secondary": 0,
            "usage": 1
        },
        "Roy": {
            "name": "Roy",
            "secondary": 0,
            "usage": 0
        },
        "Ryu": {
            "name": "Ryu",
            "secondary": 0,
            "usage": 0
        },
        "Samus": {
            "name": "Samus",
            "secondary": 1,
            "usage": 1
        },
        "Sheik": {
            "name": "Sheik",
            "secondary": 0,
            "usage": 0
        },
        "Shulk": {
            "name": "Shulk",
            "secondary": 0,
            "usage": 0
        },
        "Simon": {
            "name": "Simon",
            "secondary": 0,
            "usage": 0
        },
        "Snake": {
            "name": "Snake",
            "secondary": 0,
            "usage": 0
        },
        "Sonic": {
            "name": "Sonic",
            "secondary": 0,
            "usage": 0
        },
        "Steve": {
            "name": "Steve",
            "secondary": 0,
            "usage": 0
        },
        "Terry": {
            "name": "Terry",
            "secondary": 0,
            "usage": 0
        },
        "Toon Link": {
            "name": "Toon Link",
            "secondary": 0,
            "usage": 0
        },
        "Villager": {
            "name": "Villager",
            "secondary": 0,
            "usage": 0
        },
        "Wario": {
            "name": "Wario",
            "secondary": 0,
            "usage": 0
        },
        "Wii Fit Trainer": {
            "name": "Wii Fit Trainer",
            "secondary": 0,
            "usage": 0
        },
        "Wolf": {
            "name": "Wolf",
            "secondary": 0,
            "usage": 0
        },
        "Yoshi": {
            "name": "Yoshi",
            "secondary": 1,
            "usage": 0
        },
        "Young Link": {
            "name": "Young Link",
            "secondary": 0,
            "usage": 0
        },
        "Zelda": {
            "name": "Zelda",
            "secondary": 1,
            "usage": 0
        },
        "Zero Suit Samus": {
            "name": "Zero Suit Samus",
            "secondary": 1,
            "usage": 0
        }
    },
    "players_per_country": {
        "BR": 16
    },
    "players_per_state": {
        "AL": {
            "count": 9,
            "country_code": "BR"
        }
    }
}