{
    "braacket_link": {
        "smashbelem": "/league/smashbelem/player/02FB6496-2927-4B5F-ADC0-5220CF2F2A85?ranking=8A5FCBF3-8508-4027-AADE-65B0D7CBCB01&embed=1"
    },
    "mains": [
        {
            "icon": "/assets/images/game/ssbu/characters/villager.png",
            "name": "Villager"
        }
    ],
    "name": "Soji",
    "rank": {
        "prbth": {
            "rank": 350,
            "score": 7
        },
        "smashbelem": {
            "rank": "8",
            "score": "1002"
        }
    },
    "tournament_points": [
        7
    ],
    "tournaments": [
        {
            "name": "Smash Tuesdays 4",
            "placing": "7",
            "points": 7,
            "rank": "D"
        }
    ]
}