{
    "mains": [
        {
            "icon": "/assets/images/game/ssbu/characters/darksamus.png",
            "name": "Dark Samus"
        },
        {
            "icon": "/assets/images/game/ssbu/characters/meta_knight.png",
            "name": "Meta Knight"
        },
        {
            "icon": "/assets/images/game/ssbu/characters/wario.png",
            "name": "Wario"
        }
    ],
    "name": "LDJ | IPHILSGOOD",
    "rank": {
        "prbth": {
            "rank": 235,
            "score": 7
        },
        "ssbudf": {
            "rank": "10",
            "score": "48"
        }
    }
}